README.md
setup.py
./res/__init__.py
./res/langnames/__init__.py
./wikt2dict/__init__.py
./wikt2dict/article.py
./wikt2dict/article_o.py
./wikt2dict/article_parsers.py
./wikt2dict/config.py
./wikt2dict/evaluator.py
./wikt2dict/triangulator.py
./wikt2dict/w2d.py
./wikt2dict/wiktionary.py
./wikt2dict/external/__init__.py
./wikt2dict/external/articles.py
./wikt2dict/external/wiki.py
bin/compare_dicts.py
bin/extract_translations.py
bin/filter_in_file.py
bin/find_anomalies.py
bin/find_polygons.py
bin/find_translations.py
bin/punctuation_filter.py
bin/summarize_4lang_translations.py
bin/triangulate.py
bin/unigrams.py
res/wikicodes
res/wiktionaries-full.tsv
res/wiktionaries.tsv
res/langnames/__init__.py
res/langnames/arabic
res/langnames/aromanian
res/langnames/azeri
res/langnames/basque
res/langnames/bulgarian
res/langnames/catalan
res/langnames/chinese
res/langnames/czech
res/langnames/danish
res/langnames/dutch
res/langnames/english
res/langnames/esperanto
res/langnames/estonian
res/langnames/finnish
res/langnames/french
res/langnames/galician
res/langnames/georgian
res/langnames/german
res/langnames/greek
res/langnames/hebrew
res/langnames/hindi
res/langnames/hungarian
res/langnames/indonesian
res/langnames/italian
res/langnames/japanese
res/langnames/kazakh
res/langnames/korean
res/langnames/latin
res/langnames/lithuanian
res/langnames/macedonian
res/langnames/malagasy
res/langnames/malay
res/langnames/norwegian
res/langnames/occitan
res/langnames/persian
res/langnames/polish
res/langnames/portuguese
res/langnames/romanian
res/langnames/russian
res/langnames/serbian
res/langnames/slovak
res/langnames/slovenian
res/langnames/spanish
res/langnames/swahili
res/langnames/swedish
res/langnames/thai
res/langnames/turkish
res/langnames/ukrainian
res/langnames/vietnamese
wikt2dict/w2d.py
wikt2dict.egg-info/PKG-INFO
wikt2dict.egg-info/SOURCES.txt
wikt2dict.egg-info/dependency_links.txt
wikt2dict.egg-info/not-zip-safe
wikt2dict.egg-info/requires.txt
wikt2dict.egg-info/top_level.txt
wikt2dict/external/__init__.py
wikt2dict/external/articles.py
wikt2dict/external/wiki.py