Metadata-Version: 2.1
Name: wikt2dict
Version: 2.1.0
Summary: Wiktionary translation parser tool for many language editions.     Wikt2dict parses only the translation sections.     It also has a triangulation mode which combines the extracted translation pairs to generate new ones.
Home-page: https://github.com/HMRLKE/wikt2dict
Author: Endre Hamerlik, Judit Acs
Author-email: endre.hamerlik@fmph.uniba.sk, judit@sch.bme.hu
License: UNKNOWN
Platform: any
Classifier: Programming Language :: Python :: 3.8
Provides: wikt2dict
